CFstreamparser/__init__.py
CFstreamparser/parser.py
CFstreamparser/resolution.py
CFstreamparser/stats.py
CFstreamparser/unitcell.py
cfstreamparser-0.2.2.dist-info/licenses/LICENSE
cfstreamparser-0.2.2.dist-info/METADATA
cfstreamparser-0.2.2.dist-info/WHEEL
cfstreamparser-0.2.2.dist-info/top_level.txt
cfstreamparser-0.2.2.dist-info/RECORD
