Metadata-Version: 2.4
Name: CFstreamparser
Version: 0.2.2
Summary: Stream-file parser for CrystFEL output
Author-email: Paul Hager <paul.hager@su.se>
License: MIT License
Project-URL: Source, https://gitlab.com/kristallorakel/CFstreamparser
Classifier: Programming Language :: Python :: 3
Classifier: License :: OSI Approved :: MIT License
Classifier: Operating System :: OS Independent
Requires-Python: >=3.8
License-File: LICENSE
Dynamic: license-file
